cli/__init__.py
cli/cli.py
cli/completion.py
cli/conftest.py
cli/lark.py
cli/lark_doc.py
cli/test_cli.py
one_man_team-0.1.3.dist-info/METADATA
one_man_team-0.1.3.dist-info/WHEEL
one_man_team-0.1.3.dist-info/entry_points.txt
one_man_team-0.1.3.dist-info/top_level.txt
one_man_team-0.1.3.dist-info/RECORD
