Metadata-Version: 2.1
Name: one-man-team
Version: 0.1.3
Summary: One Man Team CLI Tool
Home-page: https://github.com/atorber/one-man-team
Author: atorber
Author-email: atorber@163.com
License: UNKNOWN
Platform: UNKNOWN
Requires-Dist: Click
Requires-Dist: python-dotenv
Requires-Dist: lark-oapi
Requires-Dist: tabulate
Requires-Dist: PyYAML
Provides-Extra: completion
Requires-Dist: click-completion; extra == "completion"
Provides-Extra: test
Requires-Dist: pytest>=6.0; extra == "test"
Requires-Dist: pytest-cov; extra == "test"
